test/__init__.py
montudor_test_repo-0.0.5.dist-info/METADATA
montudor_test_repo-0.0.5.dist-info/WHEEL
montudor_test_repo-0.0.5.dist-info/top_level.txt
montudor_test_repo-0.0.5.dist-info/RECORD
